requirements.txt
zhishuyun_scaffold/__init__.py
zhishuyun_scaffold/__version__.py
zhishuyun_scaffold/settings.py
zhishuyun_scaffold/controllers/__init__.py
zhishuyun_scaffold/controllers/base.py
zhishuyun_scaffold/exceptions/__init__.py
zhishuyun_scaffold/exceptions/api_not_implemented.py
zhishuyun_scaffold/exceptions/bad_request.py
zhishuyun_scaffold/exceptions/base.py
zhishuyun_scaffold/exceptions/invalid_token.py
zhishuyun_scaffold/exceptions/no_api.py
zhishuyun_scaffold/exceptions/no_token.py
zhishuyun_scaffold/exceptions/token_mismatched.py
zhishuyun_scaffold/exceptions/too_many_requests.py
zhishuyun_scaffold/exceptions/used_up.py
zhishuyun_scaffold/handlers/__init__.py
zhishuyun_scaffold/handlers/base.py
zhishuyun_scaffold/handlers/error.py
zhishuyun_scaffold/handlers/health.py
zhishuyun_scaffold-0.3.5.dist-info/METADATA
zhishuyun_scaffold-0.3.5.dist-info/WHEEL
zhishuyun_scaffold-0.3.5.dist-info/top_level.txt
zhishuyun_scaffold-0.3.5.dist-info/RECORD
