Metadata-Version: 2.1
Name: zhishuyun-scaffold
Version: 0.3.5
Summary: A scaffold to help you build zhishuyun api easily.
Home-page: https://github.com/ZhiShuYun/ScaffoldPython
Author: Germey
Author-email: dev@zhishuyun.com
License: MIT
Classifier: License :: OSI Approved :: MIT License
Classifier: Programming Language :: Python :: 3.7
Classifier: Programming Language :: Python :: 3.8
Classifier: Programming Language :: Python :: 3.9
Classifier: Programming Language :: Python :: 3.10
Classifier: Programming Language :: Python :: 3.11
Classifier: Programming Language :: Python :: Implementation :: CPython
Classifier: Programming Language :: Python :: Implementation :: PyPy
Requires-Python: >=3.7.0
Requires-Dist: django >=3.0.0
Requires-Dist: djangorestframework >=3.11.0
Requires-Dist: environs
Requires-Dist: loguru
Requires-Dist: tornado
